HungarianScorer/HungarianScorer.py
HungarianScorer/requirements.txt
HungarianScorer-1.0.2.dist-info/LICENSE
HungarianScorer-1.0.2.dist-info/METADATA
HungarianScorer-1.0.2.dist-info/WHEEL
HungarianScorer-1.0.2.dist-info/top_level.txt
HungarianScorer-1.0.2.dist-info/RECORD
