Metadata-Version: 2.1
Name: HungarianScorer
Version: 1.0.2
Summary: This package makes finding optimal combinations using the hungarian algorithm dead simple.
Home-page: https://github.com/johnnyweymouth/HungarianScorer.git
Author: Johnny Weymouth
Author-email: johnnycweymouth@gmail.com
Project-URL: Bug Tracker, https://github.com/johnnyweymouth/HungarianScorer/issues
License-File: LICENSE
Requires-Dist: numpy~=1.26.4
Requires-Dist: scipy~=1.13.1
